my_package/__init__.py
my_package/database.py
my_package/utils.py
mydbpackage/__init__.py
mydbpackage/database.py
mydbpackage/utils.py
tests/__init__.py
tests/test_database.py
mydbpackage-0.2.4.dist-info/METADATA
mydbpackage-0.2.4.dist-info/WHEEL
mydbpackage-0.2.4.dist-info/entry_points.txt
mydbpackage-0.2.4.dist-info/top_level.txt
mydbpackage-0.2.4.dist-info/RECORD
