Metadata-Version: 2.1
Name: mydbpackage
Version: 0.2.4
Summary: A short description of my package
Requires-Dist: mysql-connector-python
